{"assets":{"BA7DBBF40A36DA415260B5A2105B72AE":{"type":"texture","index":277,"assetRequest":{"type":"slide","state":"outgoing","slide":"F2CAC22A-F6DC-43F8-A1A2-6191EF2D74A2"},"url":"assets/BA7DBBF40A36DA415260B5A2105B72AE.svg","width":1024,"height":768},"FB98B4AEF86AB9AF5412E0DBD9763FD2":{"url":"assets/FB98B4AEF86AB9AF5412E0DBD9763FD2.svg","height":586.134765625,"movie":"cookie-monster.gif-0.0000-1.5000","width":1026.249877929688,"type":"texture","assetRequest":{"type":"slide","state":"contents","slide":"F2CAC22A-F6DC-43F8-A1A2-6191EF2D74A2"},"index":276},"cookie-monster.gif-0.0000-1.5000":{"type":"video","index":0,"assetRequest":{},"url":"assets/cookie-monster.gif-0.0000-1.5000.m4v","width":499,"height":285},"2F92F92C9ADBBAD81B82B6B5E5B81E9A":{"type":"texture","index":278,"assetRequest":{"type":"slide","state":"incoming","slide":"4B28B648-05E6-4990-8D04-C9BE40BDEED9"},"url":"assets/2F92F92C9ADBBAD81B82B6B5E5B81E9A.svg","width":1024,"height":768},"B05EAD5EB6951728A3F343C0D6D0F178":{"type":"texture","index":275,"assetRequest":{"type":"slide","state":"contents","slide":"F2CAC22A-F6DC-43F8-A1A2-6191EF2D74A2"},"url":"assets/B05EAD5EB6951728A3F343C0D6D0F178.svg","width":1030,"height":590},"498E23C82CA78A4BCD7BA88E5243B6FC":{"type":"texture","index":274,"assetRequest":{"type":"slide","state":"contents","slide":"F2CAC22A-F6DC-43F8-A1A2-6191EF2D74A2"},"url":"assets/498E23C82CA78A4BCD7BA88E5243B6FC.svg","width":1024,"height":768}},"events":[{"effects":[{"beginTime":0,"baseLayer":{"animations":[],"initialState":{"affineTransform":[1,0,0,1,0,0],"masksToBounds":false,"rotation":0,"scale":1,"position":{"pointX":512.0000000261998,"pointY":384},"width":1026.249877929688,"sublayerTransform":[1,0,0,0,0,1,0,0,0,0,1,0,0,0,0,1],"contentsRect":{"y":0,"x":0,"width":1,"height":1},"opacity":1,"edgeAntialiasingMask":15,"height":586.134765625,"hidden":false,"anchorPoint":{"pointX":0.5,"pointY":0.5}},"objectID":"BD0377F7-3B2E-455C-A48D-616A19DFC4ED","layers":[{"animations":[],"initialState":{"affineTransform":[1,0,0,1,0,0],"masksToBounds":false,"rotation":0,"scale":1,"position":{"pointX":513.1249389386439,"pointY":293.0673828125},"width":1026.249877929688,"sublayerTransform":[1,0,0,0,0,1,0,0,0,0,1,-0.0004922987690640373,0,0,0,1],"contentsRect":{"y":0,"x":0,"width":1,"height":1},"opacity":1,"edgeAntialiasingMask":15,"height":586.134765625,"hidden":false,"anchorPoint":{"pointX":0.4999999999744703,"pointY":0.5}},"layers":[{"animations":[{"repeatCount":0,"animations":[{"from":{"scalar":true},"beginTime":0,"repeatCount":0,"fillMode":"removed","property":"isPlaying","duration":0.01,"to":{"scalar":true}},{"from":{"scalar":false},"beginTime":0,"repeatCount":0,"fillMode":"removed","property":"hidden","duration":0.01,"to":{"scalar":false}}],"beginTime":1e-100,"fillMode":"both","duration":0.01}],"layers":[],"initialState":{"affineTransform":[1,0,0,1,0,0],"masksToBounds":false,"rotation":0,"scale":1,"position":{"pointX":513.1249389386439,"pointY":293.0673828125},"width":1030,"sublayerTransform":[1,0,0,0,0,1,0,0,0,0,1,0,0,0,0,1],"contentsRect":{"y":0,"x":0,"width":1,"height":1},"opacity":1,"edgeAntialiasingMask":0,"height":590,"hidden":false,"anchorPoint":{"pointX":0.5,"pointY":0.5}},"texture":"B05EAD5EB6951728A3F343C0D6D0F178"}]}]},"effects":[{"beginTime":0,"baseLayer":{"animations":[],"initialState":{"affineTransform":[1,0,0,1,0,0],"masksToBounds":false,"rotation":0,"scale":1,"position":{"pointX":512.0000000261998,"pointY":384},"width":1026.249877929688,"sublayerTransform":[1,0,0,0,0,1,0,0,0,0,1,0,0,0,0,1],"contentsRect":{"y":0,"x":0,"width":1,"height":1},"opacity":1,"edgeAntialiasingMask":15,"height":586.134765625,"hidden":false,"anchorPoint":{"pointX":0.5,"pointY":0.5}},"objectID":"BD0377F7-3B2E-455C-A48D-616A19DFC4ED","layers":[{"animations":[],"layers":[],"initialState":{"affineTransform":[1,0,0,1,0,0],"masksToBounds":false,"rotation":0,"scale":1,"position":{"pointX":513.1249389386439,"pointY":293.0673828125},"width":1030,"sublayerTransform":[1,0,0,0,0,1,0,0,0,0,1,0,0,0,0,1],"contentsRect":{"y":0,"x":0,"width":1,"height":1},"opacity":1,"edgeAntialiasingMask":0,"height":590,"hidden":true,"anchorPoint":{"pointX":0.5,"pointY":0.5}},"texture":"B05EAD5EB6951728A3F343C0D6D0F178"},{"animations":[],"layers":[],"initialState":{"affineTransform":[1,0,0,1,0,0],"masksToBounds":false,"rotation":0,"scale":1,"position":{"pointX":513.1249389648438,"pointY":293.0673828125},"width":1026.249877929688,"sublayerTransform":[1,0,0,0,0,1,0,0,0,0,1,0,0,0,0,1],"contentsRect":{"y":0,"x":0,"width":1,"height":1},"opacity":1,"edgeAntialiasingMask":15,"height":586.134765625,"hidden":false,"anchorPoint":{"pointX":0.5,"pointY":0.5}},"texture":"FB98B4AEF86AB9AF5412E0DBD9763FD2"}]},"effects":[],"movie":{"volume":1,"isStreaming":false,"isAudioOnly":false,"endTime":1.500000022351742,"startTime":0,"asset":"cookie-monster.gif-0.0000-1.5000","loopMode":"looping"},"duration":0,"type":"none","attributes":{"direction":0},"name":"renderMovie","objectID":"BD0377F7-3B2E-455C-A48D-616A19DFC4ED"}],"duration":0.01,"type":"buildIn","name":"apple:movie-start","objectID":"BD0377F7-3B2E-455C-A48D-616A19DFC4ED"}],"automaticPlay":true,"hyperlinks":[],"accessibility":[],"baseLayer":{"animations":[],"initialState":{"affineTransform":[1,0,0,1,0,0],"masksToBounds":true,"rotation":0,"scale":1,"position":{"pointX":512,"pointY":384},"width":1024,"sublayerTransform":[1,0,0,0,0,1,0,0,0,0,1,0,0,0,0,1],"contentsRect":{"y":0,"x":0,"width":1,"height":1},"opacity":1,"edgeAntialiasingMask":0,"height":768,"hidden":false,"anchorPoint":{"pointX":0.5,"pointY":0.5}},"layers":[{"animations":[],"initialState":{"affineTransform":[1,0,0,1,0,0],"masksToBounds":false,"rotation":0,"scale":1,"position":{"pointX":512,"pointY":384},"width":1024,"sublayerTransform":[1,0,0,0,0,1,0,0,0,0,1,0,0,0,0,1],"contentsRect":{"y":0,"x":0,"width":1,"height":1},"opacity":1,"edgeAntialiasingMask":15,"height":768,"hidden":false,"anchorPoint":{"pointX":0.5,"pointY":0.5}},"layers":[{"animations":[],"initialState":{"affineTransform":[1,0,0,1,0,0],"masksToBounds":false,"rotation":0,"scale":1,"position":{"pointX":512,"pointY":384},"width":1024,"sublayerTransform":[1,0,0,0,0,1,0,0,0,0,1,0,0,0,0,1],"contentsRect":{"y":0,"x":0,"width":1,"height":1},"opacity":1,"edgeAntialiasingMask":15,"height":768,"hidden":false,"anchorPoint":{"pointX":0.5,"pointY":0.5}},"layers":[{"animations":[],"layers":[],"initialState":{"affineTransform":[1,0,0,1,0,0],"masksToBounds":false,"rotation":0,"scale":1,"position":{"pointX":512,"pointY":384},"width":1024,"sublayerTransform":[1,0,0,0,0,1,0,0,0,0,1,0,0,0,0,1],"contentsRect":{"y":0,"x":0,"width":1,"height":1},"opacity":1,"edgeAntialiasingMask":0,"height":768,"hidden":false,"anchorPoint":{"pointX":0.5,"pointY":0.5}},"texture":"498E23C82CA78A4BCD7BA88E5243B6FC"}]}]},{"animations":[],"initialState":{"affineTransform":[1,0,0,1,0,0],"masksToBounds":false,"rotation":0,"scale":1,"position":{"pointX":512,"pointY":384},"width":1024,"sublayerTransform":[1,0,0,0,0,1,0,0,0,0,1,0,0,0,0,1],"contentsRect":{"y":0,"x":0,"width":1,"height":1},"opacity":1,"edgeAntialiasingMask":15,"height":768,"hidden":false,"anchorPoint":{"pointX":0.5,"pointY":0.5}},"layers":[{"animations":[],"initialState":{"affineTransform":[1,0,0,1,0,0],"masksToBounds":false,"rotation":0,"scale":1,"position":{"pointX":512.0000000261998,"pointY":384},"width":1026.249877929688,"sublayerTransform":[1,0,0,0,0,1,0,0,0,0,1,0,0,0,0,1],"contentsRect":{"y":0,"x":0,"width":1,"height":1},"opacity":1,"edgeAntialiasingMask":15,"height":586.134765625,"hidden":false,"anchorPoint":{"pointX":0.5,"pointY":0.5}},"objectID":"BD0377F7-3B2E-455C-A48D-616A19DFC4ED","layers":[{"animations":[],"layers":[],"initialState":{"affineTransform":[1,0,0,1,0,0],"masksToBounds":false,"rotation":0,"scale":1,"position":{"pointX":513.1249389386439,"pointY":293.0673828125},"width":1030,"sublayerTransform":[1,0,0,0,0,1,0,0,0,0,1,0,0,0,0,1],"contentsRect":{"y":0,"x":0,"width":1,"height":1},"opacity":1,"edgeAntialiasingMask":0,"height":590,"hidden":false,"anchorPoint":{"pointX":0.5,"pointY":0.5}},"texture":"B05EAD5EB6951728A3F343C0D6D0F178"}]}]}]}},{"effects":[{"beginTime":0,"baseLayer":{"animations":[],"initialState":{"affineTransform":[1,0,0,1,0,0],"masksToBounds":true,"rotation":0,"scale":1,"position":{"pointX":512,"pointY":384},"width":1024,"sublayerTransform":[1,0,0,0,0,1,0,0,0,0,1,0,0,0,0,1],"contentsRect":{"y":0,"x":0,"width":1,"height":1},"opacity":1,"edgeAntialiasingMask":0,"height":768,"hidden":false,"anchorPoint":{"pointX":0.5,"pointY":0.5}},"objectID":"0","layers":[{"animations":[],"initialState":{"affineTransform":[1,0,0,1,0,0],"masksToBounds":false,"rotation":0,"scale":1,"position":{"pointX":512,"pointY":384},"width":1024,"sublayerTransform":[1,0,0,0,0,1,0,0,0,0,1,-0.0004922987690640373,0,0,0,1],"contentsRect":{"y":0,"x":0,"width":1,"height":1},"opacity":1,"edgeAntialiasingMask":15,"height":768,"hidden":false,"anchorPoint":{"pointX":0.5,"pointY":0.5}},"layers":[{"animations":[],"layers":[],"initialState":{"affineTransform":[1,0,0,1,0,0],"masksToBounds":false,"rotation":0,"scale":1,"position":{"pointX":512,"pointY":384},"width":1024,"sublayerTransform":[1,0,0,0,0,1,0,0,0,0,1,0,0,0,0,1],"contentsRect":{"y":0,"x":0,"width":1,"height":1},"opacity":1,"edgeAntialiasingMask":0,"height":768,"hidden":false,"anchorPoint":{"pointX":0.5,"pointY":0.5}},"texture":"2F92F92C9ADBBAD81B82B6B5E5B81E9A"},{"animations":[{"from":{"scalar":false},"beginTime":0,"repeatCount":0,"fillMode":"both","property":"hidden","duration":0.01,"to":{"scalar":true}}],"layers":[],"initialState":{"affineTransform":[1,0,0,1,0,0],"masksToBounds":false,"rotation":0,"scale":1,"position":{"pointX":512,"pointY":384},"width":1024,"sublayerTransform":[1,0,0,0,0,1,0,0,0,0,1,0,0,0,0,1],"contentsRect":{"y":0,"x":0,"width":1,"height":1},"opacity":1,"edgeAntialiasingMask":0,"height":768,"hidden":false,"anchorPoint":{"pointX":0.5,"pointY":0.5}},"texture":"BA7DBBF40A36DA415260B5A2105B72AE"}]}]},"effects":[],"duration":0.01,"type":"transition","name":"none","objectID":"0"}],"automaticPlay":false,"hyperlinks":[],"accessibility":[],"baseLayer":{"animations":[],"initialState":{"affineTransform":[1,0,0,1,0,0],"masksToBounds":true,"rotation":0,"scale":1,"position":{"pointX":512,"pointY":384},"width":1024,"sublayerTransform":[1,0,0,0,0,1,0,0,0,0,1,0,0,0,0,1],"contentsRect":{"y":0,"x":0,"width":1,"height":1},"opacity":1,"edgeAntialiasingMask":0,"height":768,"hidden":false,"anchorPoint":{"pointX":0.5,"pointY":0.5}},"objectID":"0","layers":[{"animations":[],"initialState":{"affineTransform":[1,0,0,1,0,0],"masksToBounds":false,"rotation":0,"scale":1,"position":{"pointX":512,"pointY":384},"width":1024,"sublayerTransform":[1,0,0,0,0,1,0,0,0,0,1,-0.0004922987690640373,0,0,0,1],"contentsRect":{"y":0,"x":0,"width":1,"height":1},"opacity":1,"edgeAntialiasingMask":15,"height":768,"hidden":false,"anchorPoint":{"pointX":0.5,"pointY":0.5}},"layers":[{"animations":[],"layers":[],"initialState":{"affineTransform":[1,0,0,1,0,0],"masksToBounds":false,"rotation":0,"scale":1,"position":{"pointX":512,"pointY":384},"width":1024,"sublayerTransform":[1,0,0,0,0,1,0,0,0,0,1,0,0,0,0,1],"contentsRect":{"y":0,"x":0,"width":1,"height":1},"opacity":1,"edgeAntialiasingMask":0,"height":768,"hidden":false,"anchorPoint":{"pointX":0.5,"pointY":0.5}},"texture":"BA7DBBF40A36DA415260B5A2105B72AE"}]}]}}]}